randomcharfield/__init__.py
randomcharfield/fields.py
django_randomcharfield-0.0.3.dist-info/LICENSE
django_randomcharfield-0.0.3.dist-info/METADATA
django_randomcharfield-0.0.3.dist-info/WHEEL
django_randomcharfield-0.0.3.dist-info/top_level.txt
django_randomcharfield-0.0.3.dist-info/RECORD
