Metadata-Version: 2.1
Name: django-randomcharfield
Version: 0.0.3
Summary: An alternative to UUIDs for model fields
Home-page: https://github.com/yoongkang/django-charfield
Author: Yoong Kang Lim
Author-email: yoongkang.lim@gmail.com
License: MIT
Platform: UNKNOWN
Classifier: Programming Language :: Python :: 3
Classifier: License :: OSI Approved :: MIT License
Classifier: Operating System :: OS Independent
Requires-Python: >=3.6
Requires-Dist: django (>=2.2)
